typstdiff/__init__.py
typstdiff/comparison.py
typstdiff/errors.py
typstdiff/file_converter.py
typstdiff/main.py
typstdiff-1.0.1.dist-info/entry_points.txt
typstdiff-1.0.1.dist-info/WHEEL
typstdiff-1.0.1.dist-info/METADATA
typstdiff-1.0.1.dist-info/RECORD
