Metadata-Version: 2.1
Name: typstdiff
Version: 1.0.1
Summary: Tool made with Pandoc to compare two files with typst extension.
Author: Sara Fojt
Author-email: 01169167@pw.edu.pl
Requires-Python: >=3.10,<4.0
Classifier: Programming Language :: Python :: 3
Classifier: Programming Language :: Python :: 3.10
Requires-Dist: jsondiff (>=2.0.0,<3.0.0)
Requires-Dist: pandoc (>=2.3,<3.0)
Requires-Dist: typst (>=0.11.0,<0.12.0)
